{
    "cards" : [
        {
            "index": 1,
            "institution": "BMO",
            "longName": "BMO Student Cashback Mastercard",
            "type": "Mastercard",
            "annualFee": 0,
            "interestRate": 0.2099,
            "groceryCashback": 0.03,
            "recurringCashback": 0.01,
            "otherCashback": 0.005,
            "transportationCashback": 0.005,
            "groceryRewardCap": 500,
            "recurringRewardCap": 500,
            "transportationRewardCap": 0,
            "image": "https://www.bmo.com/dist/images/personal/credit-cards/bmo-cashback-mastercard.png",
            "visibleKeys" : [
                "longName", "institution", "type"
            ],
            "modalKeys": [
                "interestRate",
                "annualFee",
                "groceryCashback", "recurringCashback", "otherCashback", "transportationCashback",
                "groceryRewardCap", "recurringRewardCap", "transportationRewardCap"
            ]
        },
        {
            "index": 2,
            "institution": "CIBC",
            "longName": "CIBC Dividend Visa Card for Students",
            "type": "Visa",
            "annualFee": 0,
            "interestRate": 0.2099,
            "groceryCashback": 0.02,
            "recurringCashback": 0.01,
            "transportationCashback": 0.01,
            "otherCashback": 0.005,
            "rewardCapYearly": 80000,
            "overallCapYearly": 20000,
            "image": "https://www.cibc.com/content/dam/global-assets/card-art/credit-cards/dividend-cards/cibc-dividend-visa-card-for-students/cibc-dividend-visa-card-for-students-en.png/_jcr_content/renditions/cq5dam.thumbnail.319.319.png",
            "visibleKeys" : [
                "longName", "institution", "type"
            ],
            "modalKeys": [
                "longName", "institution", "type", "interestRate",
                "annualFee",
                "groceryCashback", "recurringCashback", "otherCashback", "transportationCashback",
                "rewardCapYearly", "overallCapYearly"
            ]
        },
        {
            "index": 3,
            "institution": "RBC",
            "longName": "RBC Cash Back Mastercard",
            "type": "Mastercard",
            "annualFee": 0,
            "interestRate": 0.2099,
            "groceryCashbackMax": 0.02,
            "groceryCashbackMin": 0.01,
            "otherCashbackMin": 0.005,
            "otherCashbackMax": 0.01,
            "rewardCapYearly": 120,
            "grocerySpendingCapYearly": 6000,
            "groceryRewardCap": 120,
            "nonGroceryCapYearly": 6000,
            "nonGroceryEarningsCap": 30,
            "image": "https://www.rbcroyalbank.com/credit-cards/app/assets/cards/mc1_cashbackmc_en_sm.png",
            "visibleKeys" : [
                "longName", "institution", "type"
            ],
            "modalKeys": [
                "institution", "type", "interestRate",
                "annualFee",
                "rewardCapYearly", "grocerySpendingCapYearly", "groceryRewardCap", "nonGroceryCapYearly", "nonGroceryEarningsCap"
            ]

        },
        {
            "index": 4,
            "institution": "Scotiabank",
            "longName": "Scotiabank Momentum Visa Infinite Card",
            "type": "Visa",
            "annualFee": 120,
            "interestRate": 0.2099,
            "groceryCashback": 0.04,
            "recurringCashback": 0.04,
            "transportationCashback": 0.02,
            "otherCashback": 0.01,
            "annualCap4Percent": 25000,
            "annualCap2Percent": 25000,
            "visibleKeys" : [
                "longName", "institution", "type"
            ],
            "modalKeys": [
                "institution", "type", "interestRate",
                "annualFee",
                "groceryCashback", "recurringCashback", "otherCashback", "transportationCashback",
                "annualCap4Percent", "annualCap2Percent"
            ],
            "image": "https://www.scotiabank.com/content/dam/scotiabank/canada/en/card-arts/Momentum_Visa_Infinite_ENG.png"
        },
        {
            "index": 5,
            "institution": "HSBC",
            "longName": "HSBC +Rewards Mastercard",
            "type": "Mastercard",
            "annualFee": 25,
            "interestRate": 0.119,
            "otherCashback": 0.005,
            "restaurantEntertainmentCashback": 0.01,
            "insuranceCoverage": "Assurant®",
            "applePay": "Yes",
            "zeroLiability": "Yes",
            "image": "https://www.hsbc.ca/content/dam/hsbc/ca/banking/credit-cards/plus-rewards_en_product_page_300x474.png",

            "visibleKeys": [
                "longName", "institution", "type"
            ],
            "modalKeys": [
                "interestRate",
                "annualFee",
                "insuranceCoverage",
                "restaurantEntertainmentCashback",
                "applePay",
                "zeroLiability"
            ]
        },
        {
            "index": 6,
            "institution": "RBC",
            "longName": "RBC ION+ Visa Card",
            "type": "Visa",
            "annualFee": 48,
            "interestRate": 0.2099,
            "groceryPoints": 3,
            "restaurantPoints": 3,
            "transportationPoints": 3,
            "otherPoints": 1,
            "pointsDollarsRatio": "80/11200",
            "image": "https://www.rbcroyalbank.com/credit-cards/app/assets/cards/rbc-avion-rewards-ion-plus_en_sm.png",
            "visibleKeys": [
                "longName", "institution", "type"
            ],
            "modalKeys": [
                "interestRate",
                "annualFee",
                "diningAndEntertainmentPoints",
                "insuranceCoverage",
                "applePay",
                "zeroLiability"
            ]


        }

    ]
}
